{
  "favorites" : "Juicifers Favoriter",
  "makeYourOwn" : "Gör Din Egen",
  "cancelOrder" : "Avbryt köp",
  "next" : "Nästa",
  "chooseSmoothie" : "Välj din smoothie",
  "chooseJuice" :"Välj din juice",
  "chooseType" : "Välj typ av",
  "drink" : "dryck",
  "chooseSize" : "Välj storlek",
  "ofYourDrink" : "på din dryck",
  "small" : "Liten",
  "medium" : "Mellan",
  "large" : "Stor",
  "add" : "Lägg till",
  "fruit" : "Frukt",
  "vegetable" : "Grönsaker",
  "other" : "Övrigt",
  "thankOrder" : "Tack för din beställning!",
  "yourOrder" : "Din beställning",
  "newOrder" : "Ny beställning",
  "basket" : "Kundkorg",
  "addToOrder1" : "Lägg till",
  "addToOrder2" : "fler varor",
  "pay" : "Betala",
  "ordersFinished" : "Färdiga beställningar",
  "ordersInQueue" : "Beställningar att förbereda",
  "ordersTrending" : "Populära beställningar",
  "placeOrder" : "Beställ",
  "sideorders" : "Tillbehör",
  "juice" : "Juice eller kaffedryck",
  "smoothie" : "Smoothie",
  "ingredients" : "Ingredienser",
  "with" : "med",
  "ready" : "Klart",
  "order" : "Min beställning",
  "language" : "English"
}